pydnst/__init__.py
pydnst/__main__.py
pydnst/client.py
pydnst/commander.py
pydnst/helpers.py
pydnst/message.py
pydnst/server.py
pydnst-1.0.4.dist-info/LICENSE
pydnst-1.0.4.dist-info/METADATA
pydnst-1.0.4.dist-info/WHEEL
pydnst-1.0.4.dist-info/top_level.txt
pydnst-1.0.4.dist-info/RECORD
