Metadata-Version: 2.1
Name: pydnst
Version: 1.0.4
Summary: DNS Tunneling client and server
Home-page: https://github.com/mori-b/pydnst
Author: Mori Benech
Author-email: moribirom@gmail.com
License: UNKNOWN
Keywords: dns,tunneling,dns tunneling
Platform: UNKNOWN
Classifier: Development Status :: 4 - Beta
Classifier: Intended Audience :: Information Technology
Classifier: Topic :: System :: Networking
Classifier: License :: OSI Approved :: Apache Software License
Classifier: Programming Language :: Python :: 3
Requires-Python: >=3.6
License-File: LICENSE
Requires-Dist: cryptography
Requires-Dist: rich
Requires-Dist: scapy[basic]
Requires-Dist: toml
